{
  "name": "Фолиант Душ",
  "icon": "archon:hound_pack_soul_tome",
  "category": "archon:necromancy",
  "sortnum": 1,
  "pages": [
    {
      "type": "patchouli:text",
  "text": "Фолианты Душ необходимы для добавления призывов к вашему Посоху Нежити. У вас есть шанс найти Фолианты Душ в сундуках Бастионов и Древних городов, или гарантированный шанс в $(l:archon:world/wither_tombs)Гробницах Визеров$(). Соедините их на верстаке с Посохом Нежити, чтобы добавить конкретный призыв к вашему посоху."    
    }  
  ]
}